odoo/addons/account_move_print/README.rst
odoo/addons/account_move_print/__init__.py
odoo/addons/account_move_print/__manifest__.py
odoo/addons/account_move_print/i18n/account_move_print.pot
odoo/addons/account_move_print/i18n/es.po
odoo/addons/account_move_print/i18n/hr.po
odoo/addons/account_move_print/i18n/it.po
odoo/addons/account_move_print/i18n/tr.po
odoo/addons/account_move_print/readme/CONTRIBUTORS.md
odoo/addons/account_move_print/readme/DESCRIPTION.md
odoo/addons/account_move_print/readme/USAGE.md
odoo/addons/account_move_print/report/journal_report.xml
odoo/addons/account_move_print/static/description/icon.png
odoo/addons/account_move_print/static/description/index.html
odoo_addon_account_move_print-19.0.1.0.0.2.dist-info/METADATA
odoo_addon_account_move_print-19.0.1.0.0.2.dist-info/WHEEL
odoo_addon_account_move_print-19.0.1.0.0.2.dist-info/top_level.txt
odoo_addon_account_move_print-19.0.1.0.0.2.dist-info/RECORD
