Metadata-Version: 2.1
Name: odoo-addon-account_move_print
Version: 19.0.1.0.0.2
Requires-Dist: odoo==19.0.*
Summary: Adds the option to print Journal Entries
Home-page: https://github.com/OCA/account-financial-tools
License: LGPL-3
Author: ForgeFlow, Odoo Community Association (OCA)
Author-email: support@odoo-community.org
Classifier: Programming Language :: Python
Classifier: Framework :: Odoo
Classifier: Framework :: Odoo :: 19.0
Classifier: License :: OSI Approved :: GNU Lesser General Public License v3 (LGPLv3)
